LICENSE
MANIFEST.in
README.rst
setup.py
cpffield/__init__.py
cpffield/cpffield.py
cpffield/forms.py
cpffield/models.py
cpffield/validators.py
django_cpffield.egg-info/PKG-INFO
django_cpffield.egg-info/SOURCES.txt
django_cpffield.egg-info/dependency_links.txt
django_cpffield.egg-info/top_level.txt
docs/empty.txt
tests/__init__.py
tests/settings.py
tests/test_cpffield_validator.py