Metadata-Version: 1.1
Name: django-cpffield
Version: 0.1.1
Summary: CPF Field to use in Django Model Form
Home-page: https://github.com/silviolleite/cfp-field
Author: Silvio Luis Leite
Author-email: silviolleite@gmail.com
License: MIT
Platform: UNKNOWN
Classifier: Environment :: Web Environment
Classifier: Framework :: Django
Classifier: Framework :: Django :: 2.0
Classifier: Intended Audience :: Developers
Classifier: License :: OSI Approved :: MIT License
Classifier: Operating System :: OS Independent
Classifier: Programming Language :: Python
Classifier: Programming Language :: Python :: 3.5
Classifier: Programming Language :: Python :: 3.6
